instructlab/__init__.py
instructlab/__main__.py
instructlab/_version.py
instructlab/clickext.py
instructlab/client_utils.py
instructlab/common.py
instructlab/configuration.py
instructlab/defaults.py
instructlab/feature_gates.py
instructlab/lab.py
instructlab/log.py
instructlab/utils.py
instructlab/cli/config/init.py
instructlab/cli/data/data.py
instructlab/cli/data/generate.py
instructlab/cli/data/list.py
instructlab/cli/model/chat.py
instructlab/cli/model/download.py
instructlab/cli/model/evaluate.py
instructlab/cli/model/list.py
instructlab/cli/model/remove.py
instructlab/cli/model/serve.py
instructlab/cli/model/train.py
instructlab/cli/model/upload.py
instructlab/cli/process/attach.py
instructlab/cli/process/list.py
instructlab/cli/process/process.py
instructlab/cli/rag/__init__.py
instructlab/cli/rag/convert.py
instructlab/cli/rag/ingest.py
instructlab/cli/rag/rag.py
instructlab/cli/system/info.py
instructlab/cli/system/system.py
instructlab/config/__init__.py
instructlab/config/config.py
instructlab/config/edit.py
instructlab/config/init.py
instructlab/config/show.py
instructlab/data/__init__.py
instructlab/data/generate_data.py
instructlab/data/list_data.py
instructlab/llamacpp/LICENSE
instructlab/llamacpp/README.md
instructlab/llamacpp/__init__.py
instructlab/llamacpp/llamacpp_convert_to_gguf.py
instructlab/mlx_explore/LICENSE
instructlab/mlx_explore/README.md
instructlab/mlx_explore/__init__.py
instructlab/mlx_explore/gguf_convert_to_mlx.py
instructlab/mlx_explore/utils.py
instructlab/model/__init__.py
instructlab/model/accelerated_train.py
instructlab/model/chat.py
instructlab/model/convert.py
instructlab/model/dk_bench_utils.py
instructlab/model/download.py
instructlab/model/evaluate.py
instructlab/model/full_train.py
instructlab/model/linux_test.py
instructlab/model/list.py
instructlab/model/model.py
instructlab/model/phased_training.py
instructlab/model/remove.py
instructlab/model/serve_backend.py
instructlab/model/simple_train.py
instructlab-0.26.1.dist-info/licenses/LICENSE
instructlab-0.26.1.dist-info/METADATA
instructlab-0.26.1.dist-info/WHEEL
instructlab-0.26.1.dist-info/entry_points.txt
instructlab-0.26.1.dist-info/top_level.txt
instructlab-0.26.1.dist-info/RECORD
