Metadata-Version: 2.4
Name: instructlab
Version: 0.26.1
Summary: Core package for interacting with InstructLab
Author-email: InstructLab <dev@instructlab.ai>
License: Apache-2.0 AND MIT
Project-URL: homepage, https://instructlab.ai
Project-URL: source, https://github.com/instructlab/instructlab
Project-URL: issues, https://github.com/instructlab/instructlab/issues
Classifier: Development Status :: 3 - Alpha
Classifier: Environment :: Console
Classifier: License :: OSI Approved :: Apache Software License
Classifier: License :: OSI Approved :: MIT License
Classifier: Operating System :: MacOS :: MacOS X
Classifier: Operating System :: POSIX :: Linux
Classifier: Topic :: Scientific/Engineering :: Artificial Intelligence
Classifier: Programming Language :: Python :: 3
Classifier: Programming Language :: Python :: 3.11
Classifier: Programming Language :: Python :: Implementation :: CPython
Requires-Python: >=3.11
License-File: LICENSE
Requires-Dist: boto3>=1.35.96
Requires-Dist: click<9.0.0,>=8.1.7
Requires-Dist: click-didyoumean>=0.3.0
Requires-Dist: datasets>=2.18.0
Requires-Dist: filelock
Requires-Dist: gguf>=0.6.0
Requires-Dist: GitPython>=3.1.42
Requires-Dist: httpx>=0.25.0
Requires-Dist: instructlab-eval<0.6.0,>=0.5.1
Requires-Dist: instructlab-quantize>=0.1.0
Requires-Dist: instructlab-schema>=0.4.2
Requires-Dist: instructlab-sdg<0.9.0,>=0.8.2
Requires-Dist: instructlab-training<0.11.0,>=0.10.1
Requires-Dist: llama_cpp_python[server]==0.3.6
Requires-Dist: mlx<0.6.0,>=0.5.1; sys_platform == "darwin" and platform_machine == "arm64"
Requires-Dist: numpy<2.0.0,>=1.26.4
Requires-Dist: openai>=1.13.3
Requires-Dist: peft>=0.9.0
Requires-Dist: prompt-toolkit>=3.0.38
Requires-Dist: pydantic>=2.7.4
Requires-Dist: pydantic_yaml>=1.2.0
Requires-Dist: PyYAML>=6.0.0
Requires-Dist: rich>=13.3.1
Requires-Dist: rouge-score>=0.1.2
Requires-Dist: ruamel.yaml>=0.17.0
Requires-Dist: sentencepiece>=0.2.0
Requires-Dist: tokenizers>=0.11.1
Requires-Dist: toml>=0.10.2
Requires-Dist: torch>=2.6.0
Requires-Dist: tqdm>=4.66.2
Requires-Dist: transformers>=4.41.2
Requires-Dist: trl<0.15.0,>=0.12.2
Requires-Dist: wandb>=0.16.4
Requires-Dist: xdg-base-dirs>=6.0.1
Requires-Dist: psutil>=6.0.0
Requires-Dist: huggingface_hub[hf_transfer]>=0.1.8
Requires-Dist: haystack-ai>=2.8
Requires-Dist: docling-core[chunking]>=2.10.0
Requires-Dist: docling>=2.18.0
Requires-Dist: sentence-transformers>=3.0.0
Provides-Extra: cpu
Provides-Extra: cuda
Requires-Dist: instructlab-training[cuda]>=0.10.1; extra == "cuda"
Provides-Extra: hpu
Requires-Dist: habana-torch-plugin>=1.18.0; extra == "hpu"
Requires-Dist: habana_gpu_migration>=1.18.0; extra == "hpu"
Requires-Dist: instructlab-training[hpu]>=0.10.1; extra == "hpu"
Provides-Extra: mps
Provides-Extra: rocm
Requires-Dist: instructlab-training[rocm]>=0.10.1; extra == "rocm"
Dynamic: license-file
